sfs_settings/__init__.py
sfs_settings/core_functions.py
sfs_settings/exceptions.py
sfs_settings/pseudo_variable.py
sfs_settings/py.typed
sfs_settings/utility_functions.py
sfs_settings-0.9.4.dist-info/LICENSE
sfs_settings-0.9.4.dist-info/METADATA
sfs_settings-0.9.4.dist-info/WHEEL
sfs_settings-0.9.4.dist-info/RECORD
