Metadata-Version: 2.3
Name: sfs-settings
Version: 0.9.4
Summary: Simple, flexible, and secure settings management for Python.
License: MIT
Keywords: settings,configuration,environment,secrets
Author: Anadon
Author-email: joshua.r.marshall.1991@gmail.com
Requires-Python: >=3.11,<4.0
Classifier: Development Status :: 4 - Beta
Classifier: Intended Audience :: Developers
Classifier: License :: OSI Approved :: MIT License
Classifier: Programming Language :: Python :: 3
Classifier: Programming Language :: Python :: 3.11
Classifier: Programming Language :: Python :: 3.12
Classifier: Programming Language :: Python :: 3.13
Classifier: Topic :: Software Development :: Libraries :: Python Modules
Provides-Extra: dev
Requires-Dist: keyring (>=25.6.0,<26.0.0)
Requires-Dist: pydantic (>=2.9.0,<3.0.0)
Requires-Dist: python-dotenv (>=1.1.0,<2.0.0)
Project-URL: Repository, https://github.com/anadon/sfs-settings
